MANIFEST.in
README.md
pyproject.toml
setup.py
amuse_mercury.egg-info/PKG-INFO
amuse_mercury.egg-info/SOURCES.txt
amuse_mercury.egg-info/dependency_links.txt
amuse_mercury.egg-info/requires.txt
amuse_mercury.egg-info/top_level.txt
src/amuse/community/mercury/Makefile
src/amuse/community/mercury/__init__.py
src/amuse/community/mercury/_version.py
src/amuse/community/mercury/interface.f90
src/amuse/community/mercury/interface.py
src/amuse/community/mercury/readme.txt
src/amuse/community/mercury/src/Makefile
src/amuse/community/mercury/src/README.txt
src/amuse/community/mercury/src/amuse_helpers.f90
src/amuse/community/mercury/src/big.in
src/amuse/community/mercury/src/close.in
src/amuse/community/mercury/src/close6.for
src/amuse/community/mercury/src/element.in
src/amuse/community/mercury/src/element6.for
src/amuse/community/mercury/src/files.in
src/amuse/community/mercury/src/hash.f90
src/amuse/community/mercury/src/mercury.inc
src/amuse/community/mercury/src/mercury6.man
src/amuse/community/mercury/src/mercury6_2.for
src/amuse/community/mercury/src/mercury_main.for
src/amuse/community/mercury/src/message.for
src/amuse/community/mercury/src/message.in
src/amuse/community/mercury/src/param.in
src/amuse/community/mercury/src/small.in
src/amuse/community/mercury/src/swift.inc
support/__init__.py
support/classifiers.py
support/config.py
support/generate_main.py
support/getsp.class
support/getsp.java
support/misc.py
support/setup_codes.py
support/version.py